dragonfly_iesve/__init__.py
dragonfly_iesve/__main__.py
dragonfly_iesve/_extend_dragonfly.py
dragonfly_iesve/writer.py
dragonfly_iesve/cli/__init__.py
dragonfly_iesve/cli/translate.py
dragonfly_iesve/properties/__init__.py
dragonfly_iesve/properties/model.py
dragonfly_iesve-0.2.5.dist-info/licenses/LICENSE
dragonfly_iesve-0.2.5.dist-info/METADATA
dragonfly_iesve-0.2.5.dist-info/WHEEL
dragonfly_iesve-0.2.5.dist-info/entry_points.txt
dragonfly_iesve-0.2.5.dist-info/top_level.txt
dragonfly_iesve-0.2.5.dist-info/RECORD
